pVectors/__init__.py
pVectors/vector2.py
pvectors-0.0.5.dist-info/METADATA
pvectors-0.0.5.dist-info/WHEEL
pvectors-0.0.5.dist-info/licenses/LICENSE
pvectors-0.0.5.dist-info/RECORD
