Metadata-Version: 2.4
Name: pVectors
Version: 0.0.5
Summary: A small python package for handling the storage and math behind vectors in 2d space based off the c# implementation
Project-URL: Homepage, https://github.com/Raahguu/pVectors
Project-URL: Issues, https://github.com/Raahguu/pVectors/issues
Author-email: Raahguu <raahguu@myyahoo.com>
License-Expression: MIT
License-File: LICENSE
Classifier: Operating System :: OS Independent
Classifier: Programming Language :: Python :: 3
Requires-Python: >=3.9
